


[{"content":"","date":"26 xuño 2025","externalUrl":null,"permalink":"/gl/tags/anem/","section":"Etiquetas","summary":"","title":"ANEM","type":"tags"},{"content":"A Asociación Galega de Estudantes de Matemáticas (MaEGA) nace a comezos do 2025 co obxectivo de coordinar e promover as actividades levadas a cabo polo alumnado universitario de matemáticas de Galicia.\nOs nosos proxectos # Aurias: matemáticas entre matemáticas. Auras é un programa de amadriñamento que pon en contacto a alumnas do ensino medio con interese por profundar nas matemáticas, informarse sobre a vida universitaria ou participar en actividades lúdicas como as olimpíadas matemáticas; con estudantes do grao en Matemáticas (e os dobres graos con Informática e Física). Preme para obter máis información! Máis Mates: revista estudantil. Máis Mates é a revista universitaria da facultade de matemáticas da USC. Confeccionada polo estudantado, achega artigos curtos con pequenas anécdotas sobre a historia das matemáticas, as últimas novas, entrevistas, pasatempos e pequenos petiscos teóricos de temas que, ao mellor, non se tratan con profundidade na carreira... Preme para obter máis información! Sementeira: clube olímpico de mates-USC. Sementeira é un clube de resolución de problemas de olimpíadas matemáticas. Coordinados por alumnos de grao e mestrado, lévanse a cabo seminarios semanais nos que se intenta buscar a solución, entre todo o grupo, de problemas que, sen ser complexos teoricamente, son interesantes, instrutivos e ata fermosos! Preme para acceder ao campus virtual do curso! ","date":"26 xuño 2025","externalUrl":null,"permalink":"/gl/","section":"Asociación Galega de Estudantes de Matemáticas","summary":"\u003cp\u003eA Asociación Galega de Estudantes de Matemáticas (MaEGA) nace a comezos do 2025 co obxectivo de coordinar e promover as actividades levadas a cabo polo alumnado universitario de matemáticas de Galicia.\u003c/p\u003e\n\n\n\u003ch2 class=\"relative group\"\u003eOs nosos proxectos \n    \u003cdiv id=\"os-nosos-proxectos\" class=\"anchor\"\u003e\u003c/div\u003e\n    \n    \u003cspan\n        class=\"absolute top-0 w-6 transition-opacity opacity-0 ltr:-left-6 rtl:-right-6 not-prose group-hover:opacity-100\"\u003e\n        \u003ca class=\"group-hover:text-primary-300 dark:group-hover:text-neutral-700\"\n            style=\"text-decoration-line: none !important;\" href=\"#os-nosos-proxectos\" aria-label=\"Áncora\"\u003e#\u003c/a\u003e\n    \u003c/span\u003e        \n    \n\u003c/h2\u003e\n\u003col class=\"border-l-2 border-primary-500 dark:border-primary-300 list-none\"\u003e\n\n\n\n\n\n\n\u003cli\u003e\n  \u003cdiv class=\"flex flex-start\"\u003e\n    \u003cdiv class=\"bg-primary-500 dark:bg-primary-300 text-neutral-50 dark:text-neutral-700 min-w-[30px] h-8 text-2xl flex items-center justify-center rounded-full -ml-12 mt-5\"\u003e\n      \n\n  \u003cspan class=\"relative block icon\"\u003e\n    \u003csvg xmlns=\"http://www.w3.org/2000/svg\" viewBox=\"0 0 576 512\"\u003e\n\u003cpath fill=\"currentColor\" d=\"M234.7 42.7L197 56.8c-3 1.1-5 4-5 7.2s2 6.1 5 7.2l37.7 14.1L248.8 123c1.1 3 4 5 7.2 5s6.1-2 7.2-5l14.1-37.7L315 71.2c3-1.1 5-4 5-7.2s-2-6.1-5-7.2L277.3 42.7 263.2 5c-1.1-3-4-5-7.2-5s-6.1 2-7.2 5L234.7 42.7zM46.1 395.4c-18.7 18.7-18.7 49.1 0 67.9l34.6 34.6c18.7 18.7 49.1 18.7 67.9 0L529.9 116.5c18.7-18.7 18.7-49.1 0-67.9L495.3 14.1c-18.7-18.7-49.1-18.7-67.9 0L46.1 395.4zM484.6 82.6l-105 105-23.3-23.3 105-105 23.3 23.3zM7.5 117.2C3 118.9 0 123.2 0 128s3 9.1 7.5 10.8L64 160l21.2 56.5c1.7 4.5 6 7.5 10.8 7.5s9.1-3 10.8-7.5L128 160l56.5-21.2c4.5-1.7 7.5-6 7.5-10.8s-3-9.1-7.5-10.8L128 96 106.8 39.5C105.1 35 100.8 32 96 32s-9.1 3-10.8 7.5L64 96 7.5 117.2zm352 256c-4.5 1.7-7.5 6-7.5 10.8s3 9.1 7.5 10.8L416 416l21.2 56.5c1.7 4.5 6 7.5 10.8 7.5s9.1-3 10.8-7.5L480 416l56.5-21.2c4.5-1.7 7.5-6 7.5-10.8s-3-9.1-7.5-10.8L480 352l-21.2-56.5c-1.7-4.5-6-7.5-10.8-7.5s-9.1 3-10.8 7.5L416 352l-56.5 21.2z\"/\u003e\u003c/svg\u003e\n  \u003c/span\u003e\n\n\n    \u003c/div\u003e\n    \u003cdiv class=\"block p-6 rounded-lg shadow-2xl min-w-full ml-6 mb-10 break-words\"\u003e\n      \u003cdiv class=\"flex justify-between\"\u003e\n        \n        \u003ch2 class=\"mt-0\"\u003e\n          Aurias: matemáticas entre matemáticas. \n        \u003c/h2\u003e\n        \n        \n      \u003c/div\u003e\n      \n      \u003cdiv class=\"mb-6\"\u003e\nAuras é un programa de amadriñamento que pon en contacto a alumnas do ensino medio con interese por profundar nas matemáticas, informarse sobre a vida universitaria ou participar en actividades lúdicas como as olimpíadas matemáticas; con estudantes do grao en Matemáticas (e os dobres graos con Informática e Física).\n\n\n\u003cfigure\u003e\u003ca href=\"https://maega.gal/gl/proxectos/aurias/\" target=\"_blank\"\u003e\n        \u003cimg\n          class=\"my-0 rounded-md nozoom image-proxectos\"\n          srcset=\"\n          /Logo_Aurias_completo_hu_1d4e2df8ebdac8ac.png 330w,\n          /Logo_Aurias_completo_hu_c50345aa38e2ad6f.png 660w,\n          /Logo_Aurias_completo_hu_129fa24db561e4e2.png 1024w,\n          /Logo_Aurias_completo_hu_abc9ff173e86681d.png 2x\"\n          src=\"/Logo_Aurias_completo_hu_c50345aa38e2ad6f.png\"\n          alt=\"Logo Aurias\"\n        /\u003e\n  \u003cfigcaption\u003ePreme para obter máis información!\u003c/figcaption\u003e\n  \u003c/a\u003e\n  \u003c/figure\u003e\n\u003c/div\u003e\n    \u003c/div\u003e\n  \u003c/div\u003e\n\u003c/li\u003e\n\n\n\n\n\n\n\n\n\u003cli\u003e\n  \u003cdiv class=\"flex flex-start\"\u003e\n    \u003cdiv class=\"bg-primary-500 dark:bg-primary-300 text-neutral-50 dark:text-neutral-700 min-w-[30px] h-8 text-2xl flex items-center justify-center rounded-full -ml-12 mt-5\"\u003e\n      \n\n  \u003cspan class=\"relative block icon\"\u003e\n    \u003csvg xmlns=\"http://www.w3.org/2000/svg\" viewBox=\"0 0 512 512\"\u003e\u003cpath fill=\"currentColor\" d=\"M266.3 48.3L232.5 73.6c-5.4 4-8.5 10.4-8.5 17.1v9.1c0 6.8 5.5 12.3 12.3 12.3c2.4 0 4.8-.7 6.8-2.1l41.8-27.9c2-1.3 4.4-2.1 6.8-2.1h1c6.2 0 11.3 5.1 11.3 11.3c0 3-1.2 5.9-3.3 8l-19.9 19.9c-5.8 5.8-12.9 10.2-20.7 12.8l-26.5 8.8c-5.8 1.9-9.6 7.3-9.6 13.4c0 3.7-1.5 7.3-4.1 10l-17.9 17.9c-6.4 6.4-9.9 15-9.9 24v4.3c0 16.4 13.6 29.7 29.9 29.7c11 0 21.2-6.2 26.1-16l4-8.1c2.4-4.8 7.4-7.9 12.8-7.9c4.5 0 8.7 2.1 11.4 5.7l16.3 21.7c2.1 2.9 5.5 4.5 9.1 4.5c8.4 0 13.9-8.9 10.1-16.4l-1.1-2.3c-3.5-7 0-15.5 7.5-18l21.2-7.1c7.6-2.5 12.7-9.6 12.7-17.6c0-10.3 8.3-18.6 18.6-18.6H400c8.8 0 16 7.2 16 16s-7.2 16-16 16H379.3c-7.2 0-14.2 2.9-19.3 8l-4.7 4.7c-2.1 2.1-3.3 5-3.3 8c0 6.2 5.1 11.3 11.3 11.3h11.3c6 0 11.8 2.4 16 6.6l6.5 6.5c1.8 1.8 2.8 4.3 2.8 6.8s-1 5-2.8 6.8l-7.5 7.5C386 262 384 266.9 384 272s2 10 5.7 13.7L408 304c10.2 10.2 24.1 16 38.6 16H454c6.5-20.2 10-41.7 10-64c0-111.4-87.6-202.4-197.7-207.7zm172 307.9c-3.7-2.6-8.2-4.1-13-4.1c-6 0-11.8-2.4-16-6.6L396 332c-7.7-7.7-18-12-28.9-12c-9.7 0-19.2-3.5-26.6-9.8L314 287.4c-11.6-9.9-26.4-15.4-41.6-15.4H251.4c-12.6 0-25 3.7-35.5 10.7L188.5 301c-17.8 11.9-28.5 31.9-28.5 53.3v3.2c0 17 6.7 33.3 18.7 45.3l16 16c8.5 8.5 20 13.3 32 13.3H248c13.3 0 24 10.7 24 24c0 2.5 .4 5 1.1 7.3c71.3-5.8 132.5-47.6 165.2-107.2zM0 256a256 256 0 1 1 512 0A256 256 0 1 1 0 256zM187.3 100.7c-6.2-6.2-16.4-6.2-22.6 0l-32 32c-6.2 6.2-6.2 16.4 0 22.6s16.4 6.2 22.6 0l32-32c6.2-6.2 6.2-16.4 0-22.6z\"/\u003e\u003c/svg\u003e\n  \u003c/span\u003e\n\n\n    \u003c/div\u003e\n    \u003cdiv class=\"block p-6 rounded-lg shadow-2xl min-w-full ml-6 mb-10 break-words\"\u003e\n      \u003cdiv class=\"flex justify-between\"\u003e\n        \n        \u003ch2 class=\"mt-0\"\u003e\n          Máis Mates: revista estudantil. \n        \u003c/h2\u003e\n        \n        \n      \u003c/div\u003e\n      \n      \u003cdiv class=\"mb-6\"\u003e\nMáis Mates é a revista universitaria da facultade de matemáticas da USC. Confeccionada polo estudantado, achega artigos curtos con pequenas anécdotas sobre a historia das matemáticas, as últimas novas, entrevistas, pasatempos e pequenos petiscos teóricos de temas que, ao mellor, non se tratan con profundidade na carreira... \n\n\n\u003cfigure\u003e\u003ca href=\"https://www.usc.gal/gl/centro/facultade-matematicas/revista-estudiantil-mates\" target=\"_blank\"\u003e\n        \u003cimg\n          class=\"my-0 rounded-md nozoom image-proxectos\"\n          srcset=\"\n          /Logo_MaisMates_hu_9582c8cc73838b6.png 330w,\n          /Logo_MaisMates_hu_219d9bcb5a609b57.png 660w,\n          /Logo_MaisMates_hu_9b94b750659a193e.png 1024w,\n          /Logo_MaisMates_hu_99e72c18de464b2a.png 2x\"\n          src=\"/Logo_MaisMates_hu_219d9bcb5a609b57.png\"\n          alt=\"Logo Máis Mates\"\n        /\u003e\n  \u003cfigcaption\u003ePreme para obter máis información!\u003c/figcaption\u003e\n  \u003c/a\u003e\n  \u003c/figure\u003e\n\u003c/div\u003e\n    \u003c/div\u003e\n  \u003c/div\u003e\n\u003c/li\u003e\n\n\n\n\n\n\n\n\n\u003cli\u003e\n  \u003cdiv class=\"flex flex-start\"\u003e\n    \u003cdiv class=\"bg-primary-500 dark:bg-primary-300 text-neutral-50 dark:text-neutral-700 min-w-[30px] h-8 text-2xl flex items-center justify-center rounded-full -ml-12 mt-5\"\u003e\n      \n\n  \u003cspan class=\"relative block icon\"\u003e\n    \u003csvg xmlns=\"http://www.w3.org/2000/svg\" viewBox=\"0 0 384 512\"\u003e\u003cpath fill=\"currentColor\" d=\"M112.1 454.3c0 6.297 1.816 12.44 5.284 17.69l17.14 25.69c5.25 7.875 17.17 14.28 26.64 14.28h61.67c9.438 0 21.36-6.401 26.61-14.28l17.08-25.68c2.938-4.438 5.348-12.37 5.348-17.7L272 415.1h-160L112.1 454.3zM191.4 .0132C89.44 .3257 16 82.97 16 175.1c0 44.38 16.44 84.84 43.56 115.8c16.53 18.84 42.34 58.23 52.22 91.45c.0313 .25 .0938 .5166 .125 .7823h160.2c.0313-.2656 .0938-.5166 .125-.7823c9.875-33.22 35.69-72.61 52.22-91.45C351.6 260.8 368 220.4 368 175.1C368 78.61 288.9-.2837 191.4 .0132zM192 96.01c-44.13 0-80 35.89-80 79.1C112 184.8 104.8 192 96 192S80 184.8 80 176c0-61.76 50.25-111.1 112-111.1c8.844 0 16 7.159 16 16S200.8 96.01 192 96.01z\"/\u003e\u003c/svg\u003e\n\n  \u003c/span\u003e\n\n\n    \u003c/div\u003e\n    \u003cdiv class=\"block p-6 rounded-lg shadow-2xl min-w-full ml-6 mb-10 break-words\"\u003e\n      \u003cdiv class=\"flex justify-between\"\u003e\n        \n        \u003ch2 class=\"mt-0\"\u003e\n          Sementeira: clube olímpico de mates-USC. \n        \u003c/h2\u003e\n        \n        \n      \u003c/div\u003e\n      \n      \u003cdiv class=\"mb-6\"\u003e\nSementeira é un clube de resolución de problemas de olimpíadas matemáticas. Coordinados por alumnos de grao e mestrado, lévanse a cabo seminarios semanais nos que se intenta buscar a solución, entre todo o grupo, de problemas que, sen ser complexos teoricamente, son interesantes, instrutivos e ata fermosos!\n\n\n\u003cfigure\u003e\u003ca href=\"https://cv.usc.es/course/view.php?id=54843\" target=\"_blank\"\u003e\n        \u003cimg\n          class=\"my-0 rounded-md nozoom image-proxectos\"\n          srcset=\"\n          /sementeira_hu_78a8b863a2e5878f.png 330w,\n          /sementeira_hu_1918a8e57026deab.png 660w,\n          /sementeira_hu_e5a3e63ce65a6c97.png 1024w,\n          /sementeira_hu_bed28a0ab6a21567.png 2x\"\n          src=\"/sementeira_hu_1918a8e57026deab.png\"\n          alt=\"Logo Sementeira\"\n        /\u003e\n  \u003cfigcaption\u003ePreme para acceder ao campus virtual do curso!\u003c/figcaption\u003e\n  \u003c/a\u003e\n  \u003c/figure\u003e\n\u003c/div\u003e\n    \u003c/div\u003e\n  \u003c/div\u003e\n\u003c/li\u003e\n\n\n\u003c/ol\u003e","title":"Asociación Galega de Estudantes de Matemáticas","type":"page"},{"content":"O pasado xoves tivemos o pracer de acoller unha interesante charla impartida por Pablo Soutullo, estudante do Grao en Matemáticas e membro de MaEGA. O evento tivo lugar na Facultade de Matemáticas, en colaboración coa Asociación Nacional de Estudiantes de Matemáticas (ANEM).\nPrevious Nextsads A conferencia puido seguirse tanto de maneira presencial na Facultade como en liña, a través das canles da ANEM, ofrecendo así unha experiencia accesible e interactiva. Os asistentes tiveron ocasión de formular preguntas e manter un coloquio enriquecedor co relator. Pódese ver a charla gravada a través de Twitch:\nA intervención xirou arredor do Axioma da Elección e das súas fascinantes implicacións: desde o papel fundamental dos principios axiomáticos na construción das matemáticas ata a historia, necesidade e consecuencias contraintuitivas asociadas a este axioma.\nAgardamos seguir organizando máis xornadas matemáticas coma esta e continuar fortalecendo a colaboración coa ANEM nun futuro próximo.\n","date":"26 xuño 2025","externalUrl":null,"permalink":"/gl/novas/charla-coa-anem-sobre-o-axioma-de-eleccion/","section":"Novas","summary":"\u003cp\u003eO pasado xoves tivemos o pracer de acoller unha interesante charla impartida por Pablo Soutullo, estudante do Grao en Matemáticas e membro de MaEGA. O evento tivo lugar na Facultade de Matemáticas, en colaboración coa Asociación Nacional de Estudiantes de Matemáticas (ANEM).\u003c/p\u003e\n\u003c!-- ![Cartel charla Pablo Soutullo](media/cartel_charla_pablo.png) --\u003e\n\n\n\n\n\n\n\n\n\n\n\n    \n        \n    \n\n\n\u003cdiv id=\"carousel-7f640a4c3155bb6d750dd01afab05c44\" class=\"relative\" data-twe-carousel-init data-twe-ride=\"carousel\"\u003e\n    \u003cdiv class=\"absolute right-0 bottom-0 left-0 z-[2] mx-[15%] mb-10 flex list-none justify-center p-0\"\n        data-twe-carousel-indicators\u003e\n\n        \n        \n\n        \u003cbutton type=\"button\" data-twe-target=\"#carousel-7f640a4c3155bb6d750dd01afab05c44\" data-twe-slide-to=\"0\"  data-twe-carousel-active aria-current=\"true\"  \n        class=\"mx-[3px] box-content h-[3px] w-[30px] flex-initial cursor-pointer border-0 border-y-[10px] border-solid border-transparent bg-neutral bg-clip-padding p-0 -indent-[999px] opacity-50 transition-opacity duration-[600ms] ease-[cubic-bezier(0.25,0.1,0.25,1.0)] motion-reduce:transition-none\"\n        aria-label=\"Slide 0\"\u003e\u003c/button\u003e\n\n        \n        \n\n        \u003cbutton type=\"button\" data-twe-target=\"#carousel-7f640a4c3155bb6d750dd01afab05c44\" data-twe-slide-to=\"1\"  \n        class=\"mx-[3px] box-content h-[3px] w-[30px] flex-initial cursor-pointer border-0 border-y-[10px] border-solid border-transparent bg-neutral bg-clip-padding p-0 -indent-[999px] opacity-50 transition-opacity duration-[600ms] ease-[cubic-bezier(0.25,0.1,0.25,1.0)] motion-reduce:transition-none\"\n        aria-label=\"Slide 1\"\u003e\u003c/button\u003e\n\n        \n        \n\n        \u003cbutton type=\"button\" data-twe-target=\"#carousel-7f640a4c3155bb6d750dd01afab05c44\" data-twe-slide-to=\"2\"  \n        class=\"mx-[3px] box-content h-[3px] w-[30px] flex-initial cursor-pointer border-0 border-y-[10px] border-solid border-transparent bg-neutral bg-clip-padding p-0 -indent-[999px] opacity-50 transition-opacity duration-[600ms] ease-[cubic-bezier(0.25,0.1,0.25,1.0)] motion-reduce:transition-none\"\n        aria-label=\"Slide 2\"\u003e\u003c/button\u003e\n\n        \n        \n\n        \u003cbutton type=\"button\" data-twe-target=\"#carousel-7f640a4c3155bb6d750dd01afab05c44\" data-twe-slide-to=\"3\"  \n        class=\"mx-[3px] box-content h-[3px] w-[30px] flex-initial cursor-pointer border-0 border-y-[10px] border-solid border-transparent bg-neutral bg-clip-padding p-0 -indent-[999px] opacity-50 transition-opacity duration-[600ms] ease-[cubic-bezier(0.25,0.1,0.25,1.0)] motion-reduce:transition-none\"\n        aria-label=\"Slide 3\"\u003e\u003c/button\u003e\n\n        \n        \n\n    \u003c/div\u003e\n    \u003cdiv class=\"relative w-full overflow-hidden after:clear-both after:block after:content-['']\"\u003e\n\n        \n        \n\n        \u003cdiv class=\"relative float-left -mr-[100%]  w-full transition-transform duration-[1500ms] ease-in-out motion-reduce:transition-none\"\n            data-twe-carousel-item  data-twe-carousel-active \u003e\n            \u003cdiv class=\"ratio-16-9 single_hero_background\"\u003e\n                \u003cimg src=\"/gl/novas/charla-coa-anem-sobre-o-axioma-de-eleccion/media/fotos_do_evento/charla_pablo_soutullo_1.jpeg\" class=\"block absolute top-0 object-cover w-full h-full nozoom\" alt=\"carousel image 0\"/\u003e\n            \u003c/div\u003e\n        \u003c/div\u003e\n\n        \n        \n\n        \u003cdiv class=\"relative float-left -mr-[100%]  hidden  w-full transition-transform duration-[1500ms] ease-in-out motion-reduce:transition-none\"\n            data-twe-carousel-item \u003e\n            \u003cdiv class=\"ratio-16-9 single_hero_background\"\u003e\n                \u003cimg src=\"/gl/novas/charla-coa-anem-sobre-o-axioma-de-eleccion/media/fotos_do_evento/charla_pablo_soutullo_2.jpeg\" class=\"block absolute top-0 object-cover w-full h-full nozoom\" alt=\"carousel image 1\"/\u003e\n            \u003c/div\u003e\n        \u003c/div\u003e\n\n        \n        \n\n        \u003cdiv class=\"relative float-left -mr-[100%]  hidden  w-full transition-transform duration-[1500ms] ease-in-out motion-reduce:transition-none\"\n            data-twe-carousel-item \u003e\n            \u003cdiv class=\"ratio-16-9 single_hero_background\"\u003e\n                \u003cimg src=\"/gl/novas/charla-coa-anem-sobre-o-axioma-de-eleccion/media/fotos_do_evento/charla_pablo_soutullo_3.jpeg\" class=\"block absolute top-0 object-cover w-full h-full nozoom\" alt=\"carousel image 2\"/\u003e\n            \u003c/div\u003e\n        \u003c/div\u003e\n\n        \n        \n\n        \u003cdiv class=\"relative float-left -mr-[100%]  hidden  w-full transition-transform duration-[1500ms] ease-in-out motion-reduce:transition-none\"\n            data-twe-carousel-item \u003e\n            \u003cdiv class=\"ratio-16-9 single_hero_background\"\u003e\n                \u003cimg src=\"/gl/novas/charla-coa-anem-sobre-o-axioma-de-eleccion/media/fotos_do_evento/charla_pablo_soutullo_4.jpeg\" class=\"block absolute top-0 object-cover w-full h-full nozoom\" alt=\"carousel image 3\"/\u003e\n            \u003c/div\u003e\n        \u003c/div\u003e\n\n        \n        \n\n    \u003c/div\u003e\n    \u003cbutton\n        class=\"absolute top-0 bottom-0 left-0 z-[2] flex w-[15%] items-center justify-center border-0 bg-none p-0 text-center text-white opacity-50 transition-opacity duration-150 ease-[cubic-bezier(0.25,0.1,0.25,1.0)] hover:text-white hover:no-underline hover:opacity-90 hover:outline-none focus:text-white focus:no-underline focus:opacity-90 focus:outline-none motion-reduce:transition-none\"\n        type=\"button\" data-twe-target=\"#carousel-7f640a4c3155bb6d750dd01afab05c44\" data-twe-slide=\"prev\"\u003e\n        \u003cspan class=\"inline-block h-8 w-8\"\u003e\n            \u003csvg xmlns=\"http://www.w3.org/2000/svg\" fill=\"none\" viewBox=\"0 0 24 24\" stroke-width=\"4.5\"\n                stroke=\"currentColor\" class=\"h-6 w-6\"\u003e\n                \u003cpath stroke-linecap=\"round\" stroke-linejoin=\"round\" d=\"M15.75 19.5L8.25 12l7.5-7.5\" /\u003e\n            \u003c/svg\u003e\n        \u003c/span\u003e\n        \u003cspan\n            class=\"!absolute !-m-px !h-px !w-px !overflow-hidden !whitespace-nowrap !border-0 !p-0 ![clip:rect(0,0,0,0)]\"\u003ePrevious\u003c/span\u003e\n    \u003c/button\u003e\n    \u003cbutton\n        class=\"absolute top-0 bottom-0 right-0 z-[1] flex w-[15%] items-center justify-center border-0 bg-none p-0 text-center text-white opacity-50 transition-opacity duration-150 ease-[cubic-bezier(0.25,0.1,0.25,1.0)] hover:text-white hover:no-underline hover:opacity-90 hover:outline-none focus:text-white focus:no-underline focus:opacity-90 focus:outline-none motion-reduce:transition-none\"\n        type=\"button\" data-twe-target=\"#carousel-7f640a4c3155bb6d750dd01afab05c44\" data-twe-slide=\"next\"\u003e\n        \u003cspan class=\"inline-block h-8 w-8\"\u003e\n            \u003csvg xmlns=\"http://www.w3.org/2000/svg\" fill=\"none\" viewBox=\"0 0 24 24\" stroke-width=\"4.5\"\n                stroke=\"currentColor\" class=\"h-6 w-6\"\u003e\n                \u003cpath stroke-linecap=\"round\" stroke-linejoin=\"round\" d=\"M8.25 4.5l7.5 7.5-7.5 7.5\" /\u003e\n            \u003c/svg\u003e\n        \u003c/span\u003e\n        \u003cspan\n            class=\"!absolute !-m-px !h-px !w-px !overflow-hidden !whitespace-nowrap !border-0 !p-0 ![clip:rect(0,0,0,0)]\"\u003eNextsads\u003c/span\u003e\n    \u003c/button\u003e\n\u003c/div\u003e\n\n\u003cp\u003eA conferencia puido seguirse tanto de maneira presencial na Facultade como en liña, a través das canles da ANEM, ofrecendo así unha experiencia accesible e interactiva. Os asistentes tiveron ocasión de formular preguntas e manter un coloquio enriquecedor co relator. Pódese ver a charla gravada a través de Twitch:\u003c/p\u003e","title":"Charla. \"Un guisante del tamaño del Sol. El Axioma de Elección y sus desagradables consecuencias\"","type":"novas"},{"content":"","date":"26 xuño 2025","externalUrl":null,"permalink":"/gl/tags/","section":"Etiquetas","summary":"","title":"Etiquetas","type":"tags"},{"content":"","date":"26 xuño 2025","externalUrl":null,"permalink":"/gl/authors/","section":"Fontes","summary":"","title":"Fontes","type":"authors"},{"content":"","date":"26 xuño 2025","externalUrl":null,"permalink":"/gl/authors/maega/","section":"Fontes","summary":"","title":"Maega","type":"authors"},{"content":"","date":"26 xuño 2025","externalUrl":null,"permalink":"/gl/tags/maega/","section":"Etiquetas","summary":"","title":"MaEGA","type":"tags"},{"content":"","date":"26 xuño 2025","externalUrl":null,"permalink":"/gl/novas/","section":"Novas","summary":"","title":"Novas","type":"novas"},{"content":"","date":"26 xuño 2025","externalUrl":null,"permalink":"/gl/tags/novas/","section":"Etiquetas","summary":"","title":"Novas","type":"tags"},{"content":"","date":"26 xuño 2025","externalUrl":null,"permalink":"/gl/authors/pablo_soutullo/","section":"Fontes","summary":"","title":"Pablo_soutullo","type":"authors"},{"content":"Esta semana, as facultades de toda Galicia comezaron a encherse de tarxetiñas con frases de personaxes históricos. Nós somos os culpables! Colaboramos coa asociación Enxeñería Sen Fronteiras na difusión da campaña \u0026ldquo;Todo pasa\u0026hellip; e todo queda?\u0026rdquo;.\nEn que consiste a campaña? # Cando pensamos na presencia da muller na ciencia, sempre intentamos atopar esas mulleres que, pese ás dificultades, conseguiron saír adiante e facer grandes contribucións. Procuramos mulleres que quedaron ocultas na historia, por mor da sociedade patriarcal, e mostramos os seus méritos. Esta campaña muda a filosofía: en vez de intentar buscar referentes femininas, queremos atopar a causa de que non as houbese. Así, mediante frases que dixeron os seus compañeiros homes, entendemos o motivo polo que non conseguisen prosperar. Vemos que, dende unha posición de alto prestixio, trataban ás mulleres dun xeito insultante, e non as crían capaces de igualar o que eles facían.\nEstas frases, que agora nos parecen disparatadas, non se afastan tanto doutras que escoitamos no noso día a día. A diferenza é que estas últimas están adaptadas ao noso tempo, pasando desapercibidas ou considerándose normais, igual que ocorría naquelas épocas. Por iso, dende MaEGA apoiamos un cambio de mentalidade, onde o respecto e a igualdade, en particular nas matemáticas, son prioritarias.\nDamos as grazas a Enxeñería Sen Fronteiras por deixarnos participar nesta marabillosa iniciativa, na que non só as matemáticas, senón tódalas disciplinas científicas poden fixarse e tomar conciencia.\nSe queres facer actividades tan chulas coma esta, non dubides en asociarte a Enxeñería Sen Fronteiras ou a MaEGA e participar nos nosos proxectos!!\nGalería # A campaña # Deixámosvos aquí tódalas tarxetiñas para que as poidades consultar sempre que queirades.\nA difusión # Por último, aquí podedes ver parte da pegada que tivo a campaña nas bibliotecas da USC.\nPrevious Nextsads ","date":"26 abril 2025","externalUrl":null,"permalink":"/gl/novas/campa%C3%B1a-esf-todo-pasa-e-todo-queda/","section":"Novas","summary":"\u003cp\u003eEsta semana, as facultades de toda Galicia comezaron a encherse de tarxetiñas con frases de personaxes históricos. Nós somos os culpables! Colaboramos coa asociación \u003ca href=\"https://galicia.isf.es/\" target=\"_blank\"\u003eEnxeñería Sen Fronteiras\u003c/a\u003e na difusión da campaña \u003cem\u003e\u0026ldquo;Todo pasa\u0026hellip; e todo queda?\u0026rdquo;\u003c/em\u003e.\u003c/p\u003e\n\u003cp\u003e\n    \u003cfigure\u003e\n      \u003cimg class=\"my-0 rounded-md\" loading=\"lazy\" src=\"campa%C3%B1a/Cartel_explicativo.jpeg\" alt=\"Cartel explicativo da campaña\" /\u003e\n      \n    \u003c/figure\u003e\n\u003c/p\u003e\n\n\n\u003ch2 class=\"relative group\"\u003eEn que consiste a campaña? \n    \u003cdiv id=\"en-que-consiste-a-campa%C3%B1a\" class=\"anchor\"\u003e\u003c/div\u003e\n    \n    \u003cspan\n        class=\"absolute top-0 w-6 transition-opacity opacity-0 ltr:-left-6 rtl:-right-6 not-prose group-hover:opacity-100\"\u003e\n        \u003ca class=\"group-hover:text-primary-300 dark:group-hover:text-neutral-700\"\n            style=\"text-decoration-line: none !important;\" href=\"#en-que-consiste-a-campa%C3%B1a\" aria-label=\"Áncora\"\u003e#\u003c/a\u003e\n    \u003c/span\u003e        \n    \n\u003c/h2\u003e\n\u003cp\u003eCando pensamos na presencia da muller na ciencia, sempre intentamos atopar esas mulleres que, pese ás dificultades, conseguiron saír adiante e facer grandes contribucións. Procuramos mulleres que quedaron ocultas na historia, por mor da sociedade patriarcal, e mostramos os seus méritos. Esta campaña muda a filosofía: en vez de intentar buscar referentes femininas, queremos atopar a causa de que non as houbese. Así, \u003cstrong\u003emediante frases que dixeron os seus compañeiros homes, entendemos o motivo polo que non conseguisen prosperar\u003c/strong\u003e. Vemos que, dende unha posición de alto prestixio, trataban ás mulleres dun xeito insultante, e non as crían capaces de igualar o que eles facían.\u003c/p\u003e","title":"Campaña. \"Todo pasa... e todo queda?\"","type":"novas"},{"content":"","date":"26 abril 2025","externalUrl":null,"permalink":"/gl/tags/enxe%C3%B1er%C3%ADa-sen-fronteiras/","section":"Etiquetas","summary":"","title":"Enxeñería Sen Fronteiras","type":"tags"},{"content":"","date":"26 marzo 2025","externalUrl":null,"permalink":"/gl/tags/liga-matem%C3%A1tica/","section":"Etiquetas","summary":"","title":"Liga Matemática","type":"tags"},{"content":"Acaba de rematar a fase regular da segunda edición da Liga Matemática organizada pola ANEM (Asociación Nacional de Estudantes de Matemáticas) e dende Sementeira querémonos facer eco do gran resultado obtido polo equipo da facultade («Funtor de Breogán»).\nQue é a Liga Matemática da ANEM? # A Liga Matemática é unha competición onde equipos de 30 universidades españolas se enfrontan na resolución de problemas matemáticos ao estilo das olimpíadas matemáticas. Divídense en 2 conferencias/grupos (o Abeliano e o Boreliano) de 15 equipos que se enfrontan nunha liga. Os partidos consisten en enfrontamentos 6 vs. 6, nos que ambos equipos teñen que resolver 3 problemas en 90 minutos, gañando o equipo que resolva primeiro os 3 problemas ou que, no seu defecto, resolva máis.\nLogo de completar a fase regular (a liga en ambas conferencias) os dous mellores clasificados de cada grupo clasifícanse para a final a 4 (por eliminatorias) que determina os postos de honra.\nDurante a primeira edición, no curso 23-24, o equipo da USC clasificouse para a fase final, que se realizou de xeito telemático, na que acadou a 3ª posición, só por detrás da Universidad de Almería e da Universidad de Valladolid.\nCales foron os resultados da USC na 2ª Edición da Liga Matemática? # Logo dun final apretado no grupo Boreliano, no que ata a última xornada catro equipos pelexaron polas únicas dúas prazas que daban acceso á fase final, o resultado foi o seguinte:\nPosto Universidade do Equipo Partidos Xogados Puntos Diferencial de Problemas 1º Universitat de les Illes Balears 14 34 21 2º Universidad de Valladolid 14 34 17 3º Universidade de Santiago de Compostela 14 32 13 4º Universidad Complutense de Madrid 14 31 17 5º Universidad Autónoma de Madrid 14 19 2 6º Universidad de Castilla - La Mancha 13 18 -3 7º Universidad de Almería 10 16 2 8º Universidad Rey Juan Carlos 12 16 -3 9º Universidad Politécnica de Madrid 11 13 0 10º Universidad de Sevilla 10 9 -6 11º Universidad de Granada 9 9 -6 12º Universidad de Extremadura 12 7 -16 13º Universidad de La Laguna 12 6 -14 14º Universidad de Málaga 6 4 -7 15 Universidad Nacional de Educación a Distancia 7 0 -17 O outro grupo, o Abeliano, estivo moito menos competido, sendo os tres primeiros clasificados:\nPosto Universidade do Equipo Partidos Xogados Puntos Diferencial de Problemas 1º Universitade do País Vasco 13 32 19 2º Universitat de Barcelona 13 29 14 3º Universidad de Cantabria 14 28 8 \u0026hellip; \u0026hellip; \u0026hellip; \u0026hellip; \u0026hellip; Polo tanto, aínda que a USC non se clasificara para a fase final a catro, foi o 4º equipo (de 30!!) con máis puntos no global de ambas conferencias, resolvendo en media máis de 2 problemas por partido. Un resultado para sentirnos moi orgullosos do traballo realizado e esperanzados de que máis pronto que tarde os éxitos chegarán.\nParabéns para os membros do equipo da USC que participaron este ano na competición: Inácio Suárez, Iván Castro, Antón Figueroa, Raquel Freire, Carla Dopazo, Pablo Soutullo, Martín García, Ada Domínguez, Francisco Morales, Yago Iglesias, Ángel Rey, Diego Fernández e Laura Salgueiro.\nComo apuntarse? Ti tamén podes participar! # O equipo que participa na Liga Matemática en representación da USC escóllese de xeito aberto a través da participación nunhas batallas matemáticas que se celebran na nosa facultade tódolos anos a mediados de setembro. Nelas, resólvense un feixe de problemas por grupos, para logo levar a cabo unha \u0026ldquo;batalla\u0026rdquo; na que, alternativamente para cada problema, un dos equipos trata de defender a corrección da súa solución do problema mentres que o outro trata de xustificar que non é válida. En función do grao de convencemento que logre acadar cada equipo consegue unha maior puntuación, gañando o equipo que obteña máis puntos.\nIndependentemente do resultado, e de quen poida resultar seleccionado segundo o seu rendemento para participar no equipo, invitámosvos a participar nas batallas por si mesmas e pasar un rato ameno con nós a comezos do vindeiro curso.\n","date":"26 marzo 2025","externalUrl":null,"permalink":"/gl/novas/resultado-liga-matematica-2025/","section":"Novas","summary":"\u003cp\u003eAcaba de rematar a fase regular da segunda edición da Liga Matemática organizada pola ANEM (Asociación Nacional de Estudantes de Matemáticas) e dende Sementeira querémonos facer eco do gran resultado obtido polo equipo da facultade (\u003cem\u003e«Funtor de Breogán»\u003c/em\u003e).\u003c/p\u003e\n\n\n\u003ch2 class=\"relative group\"\u003eQue é a Liga Matemática da ANEM? \n    \u003cdiv id=\"que-%C3%A9-a-liga-matem%C3%A1tica-da-anem\" class=\"anchor\"\u003e\u003c/div\u003e\n    \n    \u003cspan\n        class=\"absolute top-0 w-6 transition-opacity opacity-0 ltr:-left-6 rtl:-right-6 not-prose group-hover:opacity-100\"\u003e\n        \u003ca class=\"group-hover:text-primary-300 dark:group-hover:text-neutral-700\"\n            style=\"text-decoration-line: none !important;\" href=\"#que-%C3%A9-a-liga-matem%C3%A1tica-da-anem\" aria-label=\"Áncora\"\u003e#\u003c/a\u003e\n    \u003c/span\u003e        \n    \n\u003c/h2\u003e\n\u003cp\u003eA Liga Matemática é unha competición onde equipos de 30 universidades españolas se enfrontan na resolución de problemas matemáticos ao estilo das olimpíadas matemáticas. Divídense en 2 conferencias/grupos (o Abeliano e o Boreliano) de 15 equipos que se enfrontan nunha liga. Os partidos consisten en enfrontamentos 6 vs. 6, nos que ambos equipos teñen que resolver 3 problemas en 90 minutos, gañando o equipo que resolva primeiro os 3 problemas ou que, no seu defecto, resolva máis.\u003c/p\u003e","title":"O equipo da USC remata 5º na edición 24-25 da Liga Matemática da ANEM","type":"novas"},{"content":"","date":"26 marzo 2025","externalUrl":null,"permalink":"/gl/authors/sementeira/","section":"Fontes","summary":"","title":"Sementeira","type":"authors"},{"content":"","date":"26 marzo 2025","externalUrl":null,"permalink":"/gl/tags/sementeira/","section":"Etiquetas","summary":"","title":"Sementeira","type":"tags"},{"content":"","date":"9 marzo 2025","externalUrl":null,"permalink":"/es/tags/noticias/","section":"Etiquetas","summary":"","title":"Noticias","type":"tags"},{"content":"","date":"15 febreiro 2025","externalUrl":null,"permalink":"/gl/tags/a-asociaci%C3%B3n/","section":"Etiquetas","summary":"","title":"A Asociación","type":"tags"},{"content":"","date":"15 febreiro 2025","externalUrl":null,"permalink":"/gl/authors/aurias/","section":"Fontes","summary":"","title":"Aurias","type":"authors"},{"content":"Aurias é un proxecto de MaEGA, a Asociación Galega de Estudantes de Matemáticas, creado neste 2025 para promover a participación de rapazas de entre trece e dezasete anos en múltiples actividades asociadas coas matemáticas, particularmente nas Olimpíadas Matemáticas e outras competicións semellantes. A iniciativa xorde pola preocupación das estudantes do Grao en Matemáticas ante a baixa porcentaxe de participación de mulleres nestas actividades. Por exemplo, este ano só houbo un 28% de participación feminina na Olimpíada de Bacharelato, que se traduce en 101 rapaces e 40 rapazas.\nSábese que a primeiro de carreira de matemáticas chegan unhas sesenta mulleres cada curso, isto é case un 50% do total de matriculados, polo que resulta estraña esa diferenza. Aurias nace para reducir esta distancia.\nPara isto propoñemos un programa de amadriñamento, xunto con outras actividades asociadas.\nEste programa busca conectar ás rapazas interesadas con mulleres estudantes do Grao en Matemáticas, do Dobre Grao en Matemáticas e Enxeñaría Informática e do Dobre Grao de Física e Matemáticas, que se reunirían con estas unha vez cada dúas semanas de forma telemática e cun horario flexible ca fin de achegarlles esta ciencia de forma máis persoal e con maior facilidade. Neses encontros poderán falar sobre o mundo universitario, en particular, o asociado cas matemáticas e Santiago de Compostela, tamén tratarán e discutirán problemas tipo olimpíada matemática, podendo recibir formación específica e sempre dende un enfoque orientado á aprendizaxe personalizada e ao desenvolvemento das capacidades e razoamentos matemáticos. O período lectivo sería dende marzo a xaneiro, con descansos en maio, xullo, agosto, finais de decembro e xaneiro.\nContamos neste proxecto coa colaboración do Clube Olímpico da Facultade de Matemáticas, Sementeira, creado no 2017 e con ampla experiencia na preparatoria e participación de concursos matemáticos nacionais e internacionais. Desta colaboración xorde un manual de preparación, co que poderán contar todas as participantes do proxecto.\nSendo os obxectivos desta iniciativa achegarlles matemáticas universitarias, moi distintas das cursadas no ensino medio, ás participantes e, como se dixo no inicio, motivalas a participar en actividades matemáticas, como poden ser o concurso Explícoche Matemáticas 2.0 ou as Olimpíadas matemáticas e un encontro presencial opcional entre madriñas e afilladas.\nSe queres incribirte, podes facelo a través deste enlace seguindo os seguintes pasos:\nEnche o formulario cun dos teus titores legais. Recibirás un correo onde se che asigna praza e madriña. En menos dunha semana, a túa madriña se poñerá en contacto contigo para concretar un horario. Desfrutarás das sesións. Para poder garantir a praza, será necesario responder aos correos en, como máximo, unha semana. Se tes calquera dúbida, podes contactarnos a través do correo auriasmat@gmail.com.\nPor parte da USC, este proxecto conta co apoio e a colaboración da: ","date":"15 febreiro 2025","externalUrl":null,"permalink":"/gl/proxectos/aurias/","section":"Proxectos","summary":"\u003cp\u003eAurias é un proxecto de MaEGA, a Asociación Galega de Estudantes de Matemáticas, creado neste 2025 para promover a participación de rapazas de entre trece e dezasete anos en múltiples actividades asociadas coas matemáticas, particularmente nas Olimpíadas Matemáticas e outras competicións semellantes. A iniciativa xorde pola preocupación das estudantes do Grao en Matemáticas ante a baixa porcentaxe de participación de mulleres nestas actividades. Por exemplo, este ano só houbo un 28% de participación feminina na Olimpíada de Bacharelato, que se traduce en 101 rapaces e 40 rapazas.\u003c/p\u003e","title":"Aurias","type":"proxectos"},{"content":"","date":"15 febreiro 2025","externalUrl":null,"permalink":"/gl/proxectos/","section":"Proxectos","summary":"","title":"Proxectos","type":"proxectos"},{"content":"","date":"15 febreiro 2025","externalUrl":null,"permalink":"/gl/tags/proxectos/","section":"Etiquetas","summary":"","title":"Proxectos","type":"tags"},{"content":"","date":"11 febreiro 2025","externalUrl":null,"permalink":"/gl/asociacion/","section":"Asociación","summary":"","title":"Asociación","type":"asociacion"},{"content":"","date":"11 febreiro 2025","externalUrl":null,"permalink":"/gl/tags/documentaci%C3%B3n/","section":"Etiquetas","summary":"","title":"Documentación","type":"tags"},{"content":" Disposicións xerais # Artigo 1: Denominación e natureza # Coa denominación de “Asociación Galega de Estudantes de Matemáticas” (MaEGA), constitúese unha organización universitaria de natureza asociativa e sen ánimo de lucro, rexida por principios democráticos, de igualdade, laicos e sen vinculación a ningunha organización polı́tica.\nArtigo 2: Personalidade xurı́dica # A asociación constituı́da ten personalidade xurı́dica propia e plena capacidade de obrar para cumprir os fins para os que foi creada, sempre respectando os seus principios e a legalidade vixente.\nArtigo 3: Domicilio # O domicilio social da asociación queda establecido no Local de Estudantes da Facultade de Matemáticas da Universidade de Santiago de Compostela, Rúa de Lope Gómez de Marzoa, s/n, 15705 Santiago de Compostela, A Coruña. Á caixa de correo electrónico é matematicas.estudantes@usc.gal. Artigo 4: Ámbito de actuación # O seu principal ámbito de actuación é a Universidade de Santiago de Compostela, de agora en adiante USC, e, en especial, a Facultade de Matemáticas desta. Malia isto, a asociación poderá colaborar de forma activa con estudantes de toda Galicia e con outras asociacións de actuación nacional coas que comparta fins.\nArtigo 5: Duración # A asociación constitúese por tempo indefinido e rexerase segundo os principios democráticos contidos no marco da Constitución do Estado e segundo as necesidades e fins polos que foi creada.\nArtigo 6: Fins # A existencia desta asociación ten como fins:\nDefinir unha estrutura propia no estudantado de Matemáticas da USC, constituı́ndose como interlocutora ante o Decanato da Facultade de Matemáticas e as institucións oportunas e unificando as iniciativas destes estudantes. Colaborar con asociacións de carácter local ou estatal con fins semellantes aos propios. Defender os dereitos e intereses do estudantado universitario galego de matemáticas. Servir como foro de discusión e actuación de todas as persoas socias. Ofrecer a oportunidade ao estudantado de matemáticas de organizar actividades formativas e lúdicas para toda a comunidade educativa. Fomentar unha actitude crı́tica, activa e participativa nos eidos da vida estudantil. Esixir e promover activamente a mellora da calidade docente e a cultura matemática. Difundir e defender as matemáticas en galego. Promover e potenciar a participación feminina nas matemáticas, ası́ como defender a igualdade de acción e oportunidades. Para o cumprimento destas fins a Asociación poderá organizar e participar en reunións, conferencias, actividades culturais ou calquera outro evento que considere oportuno.\nDas persoas socias # Artigo 7: Clases de persoas socias # Existen dúas clases de persoas socias, non incompatibles entre elas:\nDe número, que gozan de actuación democrática na asociación e cuxos dereitos e deberes se estipulan no resto de artigos desta sección. De honra, nomeadas de xeito extraordinario pola Directiva e unicamente con carácter simbólico. Artigo 8: Requisitos de membresı́a # Para adquirir a condición de persoa socia requı́rese ser persoa fı́sica e ter interese no desenvolvemento das fins da asociación. As persoas asociadas serán estudantes interesados polas matemáticas no ámbito galego, traballadores predoutorais ou con intereses semellantes a estes. Será prioritario, pero non necesario, para gozar da calidade de persoa socia, avogar polo estudantado nalgún órgano de representación oficial. Quen desexar ser persoa socia da asociación deberá comunicalo á Secretarı́a, quen certificará, ou non, a condición de socia. Artigo 9: Perda da condición de persoa socia # A condición de persoa socia pérdese:\nPor vontade propia, que se fará efectiva mediante presentación de renuncia, por escrito á Directiva. A renuncia terá efectos desde a data da súa presentación. Por incumprimento dos presentes Estatutos, outros acordos da asociación ou atentado contra os fins ou imaxe desta. Por incapacidade, inhabilitación ou incompatibilidade. Por falecemento da persoa fı́sica, salvo no caso de socia de honra. A perda da condición de persoa socia non exime de satisfacer as obrigas que se teñan pendentes para con a asociación. Artigo 10: Dereitos das persoas socias # Son dereitos os seguintes:\nParticipar, colaborar ou organizar as actividades da asociación. Ser electoras e elixibles para os cargos dos órganos de goberno. Participar nas asembleas con voz e voto. Recibir información da composición dos órganos de representación da asociación, do seu estado de contas e do desenvolvemento da súa actividade. Acceder á documentación da asociación a través dos órganos de representación. Ser informadas e oı́das con carácter previo á toma de medidas disciplinarias xustificadas contra elas segundo o disposto no artigo 2. Impugnar os acordos dos órganos da asociación que estime contrarios á lei ou ós estatutos. Artigo 11: Obrigas das persoas socias # Son obrigas as seguintes:\nCompartir as finalidades últimas da asociación e colaborar para a súa consecución. Desempeñar as actividades para as que foron elixidas. Asistir ás asembleas e demais actos organizados pola asociación. Órganos da asociación # Artigo 12: A organización da asociación # O órgano de goberno da asociación é a Asemblea Xeral e o órgano de representación é a Directiva, que adoptarán os seus acordos de conformidade co principio maioritario ou de democracia interna.\nArtigo 13: A Asemblea Xeral # A Asemblea Xeral é o órgano supremo de goberno da asociación. Está integrada por tódalas persoas socias e deberá reunirse segundo consta nos presentes Estatutos. A asociación convocará reunións onde se expresará a súa vontade. As reunións da Asemblea Xeral poden ser ordinarias ou extraordinarias.\nArtigo 14: Convocatoria de Asemblea Ordinaria # A Asemblea Ordinaria será convocada como mı́nimo unha vez ao ano. Convocarase unha Asemblea Ordinaria tras a elección de representantes do sector do Estudantado de Grao e Máster na Xunta de Facultade (de Matemáticas) da USC. As Asembleas Ordinarias serán convocadas e presididas pola presidencia. Esta función pode ser delegada na vicepresidencia.\nAs convocatorias das Asembleas serán notificadas pola Secretarı́a a todas as persoas socias mediante unha canle apropiada e comunicando todos os detalles da mesma, tales como hora, lugar e puntos do dı́a, cunha antelación mı́nima de 48 horas.\nArtigo 15: Convocatoria de Asemblea Extraordinaria # As reunións extraordinarias celebraranse cando as circunstancias o aconsellen, cando o acorde a Directiva ou cando o soliciten por escrito o 20 % das persoas socias.\nArtigo 16: Constitución e quórum de convocatoria # As asembleas xerais, tanto ordinarias como extraordinarias, terán unha única convocatoria e quedarán validamente constituı́das sempre que estean presentes, como mı́nimo, as persoas que ostenten a presidencia e a secretarı́a ou as persoas nas que deleguen.\nArtigo 17: Facultades da Asemblea # Son competencias da Asemblea:\nNomear os membros da Directiva. Debater propostas e/ou informar sobre queixas do estudantado. Rexeitar ou revocar decisións da Directiva. Aprobar ou rexeitar propostas de calquera das persoas socias. Aprobar informes económicos. Modificar os Estatutos e/ou calquera normativa interna pertinente. A constitución de federacións ou integración nelas. Acordar a transformación da asociación. A disolución da Asociación. Artigo 18: Adopción de acordos # Os acordos da Asemblea Xeral adoptaranse por maiorı́a simple das persoas presentes ou representadas, cando os votos afirmativos superen aos negativos, non sendo computables a estes efectos os votos nulos, en branco nin as abstencións. En caso de empate, o voto da Presidencia será o decisivo.\nArtigo 19: A Directiva # A Directiva estará formada pola Presidencia, a Vicepresidencia, a Secretarı́a, a Tesourarı́a e as Vogalı́as que estes designen mediante acordo. Cada unha é un órgano unipersoal, podendo ser designada a mesma persoa fı́sica para un máximo de dous órganos de ası́ o decidir a Asemblea. A Asemblea asegurará a representación feminina na Directiva, de acordo cos principios de igualdade da Asociación.\nArtigo 20: Eleccións # A Presidencia, a Vicepresidencia, a Secretarı́a e a Tesourerı́a serán elixidas de forma anual por democracia directa tras as eleccións de representantes en Xunta de Facultade da USC. Calquera persoa socia pode ser obxecto de reelección indefinidamente.\nArtigo 21: Funcións da Directiva # É función da Directiva programar e dirixir as actividades sociais e levar a xestión administrativa e económica da Asociación, someter á aprobación da asemblea xeral o orzamento anual de ingresos e gastos, ası́ como o estado de contas do ano anterior. Adicionalmente, a Directiva encargarase de interpretar os preceptos contidos nestes Estatutos e cubrir as súas lagoas, ası́ como de asegurar o seu cumprimento, sempre someténdose á normativa legal vixente en materia de asociacións.\nArtigo 22: A Presidencia # O/a presidente/a da Asociación asume a representación legal da mesma e executará os acordos adoptados pola Directiva e a Asemblea, presidindo as sesións que celebren unha e outra. A Presidencia encargase de convocar as Asembleas Ordinarias e as eleccións da Directiva e de propor e dirixir o plan de actividades anual da asociación. Tamén coordina as posibles relacións con outras entidades, organizacións ou asociacións que sexan establecidas.\nArtigo 23: A Vicepresidencia # É función da Vicepresidencia realizar as funcións da Presidencia que esta decida delegar polo ben da asociación, ası́ como substituı́r á Presidencia en casos de vacante, ausencia ou enfermidade.\nArtigo 24: A Secretarı́a # É función da Secretarı́a xestionar as adhesións da asociación, ası́ como as solicitudes de novo acceso. Ademais, encargarase de custodiar e administrar as actas e o resto de documentación da asociación, ası́ como da comunicación a organismos superiores de modificacións en relación á información legal ou estado da asociación.\nArtigo 25: A Tesourarı́a # A Tesourarı́a recadará e custodiará os fondos pertencentes á Asociación, dará cumprimento ás ordes de pagamento que expida o presidente, dirixirá a contabilidade da Asociación, tomará razón e levará conta dos ingresos e dos gastos sociais.\nArtigo 26: As vogalı́as # As vogalı́as son creadas e suprimidas segundo necesidade pola Directiva co fin de delegar nelas a preparación e coordinación de actos e actividades, ou de acadar das mesmas as informacións necesarias. Na creación da asociación propóñense tres:\nDinamización sociocultural e igualdade Xestión académica Comunicación e redes que poderán ser conservadas ou suprimidas cando ası́ o considere a Directiva. Ademais, créanse vogalı́as de carácter especial para coordinar grandes iniciativas de duración indefinida e anexas á asociación:\nCoordinador de Sementeira Editor de MáisMates Estas desenvolverán as súas propias estruturas de coordinación lideradas pola figura da vogalı́a e poderán ser conservadas ou suprimidas cando ası́ o considere a Directiva.\nRéxime económico # Artigo 27: Patrimonio inicial # A asociación carece de patrimonio ao consituı́rse e o lı́mite do orzamento anual non excederá de 120.202,42€.\nArtigo 28: Recursos económicos # A asociación poderá ser financiada a través de\nAs doazóns ou subvencións que poidan conceder órganos públicos, entidades privadas ou particulares. Os ingresos que se poidan recibir polo desenvolvemento das actividades da asociación. Calquera outro ingreso admitido pola normativa vixente para actividades non lucrativas. Artigo 29: Contas anuais # A administración dos fondos da Asociación levarase a cabo sometida á correspondente intervención e coa publicidade suficiente, co fin de que os socios poidan ter coñecemento periodicamente do destino dos fondos, sen prexuı́zo do dereito consignado a este respecto no artigo 5 destes Estatutos.\nArtigo 30: Destino de ingresos a fins da asociación # Como entidade sen ánimo de lucro, os beneficios obtidos derivados do exercicio de actividades económicas, incluı́das as prestacións de servizos, destinaranse exclusivamente ao cumprimento dos fins da asociación. En ningún caso, estes beneficios poderán ser repartidos entre as persoas socias ou calquera outra persoa fı́sica ou xurı́dica con interese lucrativo.\nDisolución da Asociación # Artigo 31: Causas de disolución # A asociación disolverase polas seguintes causas:\nPor acordo maioritario da Asemblea. Por causas determinadas na lexislación vixente. Por sentenza xudicial firme. Artigo 32: Liquidación # A disolución da asociación abrirá o perı́odo de liquidación, ata cuxo fin a entidade conservará súa personalidade xurı́dica. O patrimonio resultante, logo de efectuadas as operacións previstas na Lei de Asociacións, destinarase a entidade non lucrativas que persigan fins de interese xeneral análogos aos realizados pola mesma. Sobre a lexislación da asociación # Artigo 33: Modificación dos Estatutos # Os presentes Estatutos poderán ser modificados se unha maiorı́a de 2/3 dunha Asemblea Extraordinaria ası́ o ratificara.\nArtigo 34: Regulamento de Réxime Interno # O previsto nestes Estatutos poderá ser complementado por un Regulamento de Réxime Interno, aprobado en Asemblea, onde sexan desenvoltas outras materias non contempladas.\nDisposicións finais # Disposición final primeira # Os presentes Estatutos entrarán en vigor tras a tramitación por parte do Rexistro da USC (11/02/2025).\nDisposición final segunda # En todo canto non estea previsto nos presentes Estatutos se aplicará a Lei Orgánica 1/2002, do 22 de marzo, reguladora do Dereito de Asociación e demais disposicións complementarias.\n","date":"11 febreiro 2025","externalUrl":null,"permalink":"/gl/asociacion/estatutos/","section":"Asociación","summary":"\u003ch2 class=\"relative group\"\u003eDisposicións xerais \n    \u003cdiv id=\"disposici%C3%B3ns-xerais\" class=\"anchor\"\u003e\u003c/div\u003e\n    \n    \u003cspan\n        class=\"absolute top-0 w-6 transition-opacity opacity-0 ltr:-left-6 rtl:-right-6 not-prose group-hover:opacity-100\"\u003e\n        \u003ca class=\"group-hover:text-primary-300 dark:group-hover:text-neutral-700\"\n            style=\"text-decoration-line: none !important;\" href=\"#disposici%C3%B3ns-xerais\" aria-label=\"Áncora\"\u003e#\u003c/a\u003e\n    \u003c/span\u003e        \n    \n\u003c/h2\u003e\n\n\n\u003ch3 class=\"relative group\"\u003eArtigo 1: Denominación e natureza \n    \u003cdiv id=\"artigo-1-denominaci%C3%B3n-e-natureza\" class=\"anchor\"\u003e\u003c/div\u003e\n    \n    \u003cspan\n        class=\"absolute top-0 w-6 transition-opacity opacity-0 ltr:-left-6 rtl:-right-6 not-prose group-hover:opacity-100\"\u003e\n        \u003ca class=\"group-hover:text-primary-300 dark:group-hover:text-neutral-700\"\n            style=\"text-decoration-line: none !important;\" href=\"#artigo-1-denominaci%C3%B3n-e-natureza\" aria-label=\"Áncora\"\u003e#\u003c/a\u003e\n    \u003c/span\u003e        \n    \n\u003c/h3\u003e\n\u003cp\u003eCoa denominación de “Asociación Galega de Estudantes de Matemáticas” (MaEGA), constitúese unha\norganización universitaria de natureza asociativa e sen ánimo de lucro, rexida por principios democráticos,\nde igualdade, laicos e sen vinculación a ningunha organización polı́tica.\u003c/p\u003e","title":"Estatutos MaEGA","type":"asociacion"},{"content":"","externalUrl":null,"permalink":"/gl/categories/","section":"Categories","summary":"","title":"Categories","type":"categories"},{"content":"","externalUrl":null,"permalink":"/gl/series/","section":"Series","summary":"","title":"Series","type":"series"}]